[
    {
        "model": "djangorarapi.category",
        "pk": 1,
        "fields": {
            "label": "Green Energy"
        }
    },
    {
        "model": "djangorarapi.category",
        "pk": 2,
        "fields": {
            "label": "Home Defense"
        }
    },
    {
        "model": "djangorarapi.category",
        "pk": 3,
        "fields": {
            "label": "Healthcare"
        }
    },
    {
        "model": "djangorarapi.category",
        "pk": 4,
        "fields": {
            "label": "Business"
        }
    }
]